cute_robot_voice/__init__.py
cute_robot_voice/cute_robot_voice.py
cute_robot_voice-1.1.1.dist-info/LICENSE
cute_robot_voice-1.1.1.dist-info/METADATA
cute_robot_voice-1.1.1.dist-info/WHEEL
cute_robot_voice-1.1.1.dist-info/top_level.txt
cute_robot_voice-1.1.1.dist-info/RECORD
