Metadata-Version: 2.1
Name: cute-robot-voice
Version: 1.1.1
Summary: A package for generating cute robot voices
Home-page: https://github.com/Tushar552/cute-robot-voice
Author: Tushar Raha
Author-email: tusharraha552@gmail.com
License: UNKNOWN
Platform: UNKNOWN
Classifier: Programming Language :: Python :: 3
Classifier: License :: OSI Approved :: MIT License
Classifier: Operating System :: OS Independent
License-File: LICENSE
Requires-Dist: gtts
Requires-Dist: numpy
Requires-Dist: pydub
Requires-Dist: scipy
Requires-Dist: simpleaudio
